LICENSE
MANIFEST.in
README.rst
setup.py
docs/Makefile
docs/api.rst
docs/changelog.rst
docs/conf.py
docs/contents.rst.inc
docs/filtering.rst
docs/index.rst
docs/installation.rst
docs/integration.rst
docs/quickstart.rst
docs/searching.rst
docs/snippets.rst
docs/_static/.gitignore
sphinxit/__init__.py
sphinxit/search.py
sphinxit/core/__init__.py
sphinxit/core/exceptions.py
sphinxit/core/lexemes.py
sphinxit/core/processor.py
sphinxit/tests/__init__.py
sphinxit/tests/test_core.py
sphinxit/tests/test_processor.py
sphinxit_fc.egg-info/PKG-INFO
sphinxit_fc.egg-info/SOURCES.txt
sphinxit_fc.egg-info/dependency_links.txt
sphinxit_fc.egg-info/requires.txt
sphinxit_fc.egg-info/top_level.txt