Metadata-Version: 1.1
Name: sphinxit-fc
Version: 0.3
Summary: Lite and powerful SphinxQL query constructor
Home-page: https://github.com/futurecolors/sphinxit
Author: Roman Semirook
Author-email: semirook@gmail.com
License: BSD
Platform: UNKNOWN
Classifier: Development Status :: 4 - Beta
Classifier: Intended Audience :: Developers
Classifier: License :: OSI Approved :: BSD License
Classifier: Operating System :: OS Independent
Classifier: Programming Language :: Python
Classifier: Topic :: Software Development :: Libraries :: Python Modules
